llama_index/packs/sub_question_weaviate/__init__.py
llama_index/packs/sub_question_weaviate/base.py
llama_index_packs_sub_question_weaviate-0.4.1.dist-info/METADATA
llama_index_packs_sub_question_weaviate-0.4.1.dist-info/WHEEL
llama_index_packs_sub_question_weaviate-0.4.1.dist-info/licenses/LICENSE
llama_index_packs_sub_question_weaviate-0.4.1.dist-info/RECORD
