Metadata-Version: 2.4
Name: llama-index-packs-sub-question-weaviate
Version: 0.4.1
Summary: llama-index packs sub_question_weaviate integration
Author-email: Your Name <you@example.com>
Maintainer: erika-cardenas
License-Expression: MIT
License-File: LICENSE
Keywords: index,query,weaviate
Requires-Python: <4.0,>=3.9
Requires-Dist: llama-index-core<0.15,>=0.13.0
Requires-Dist: llama-index-vector-stores-weaviate<2,>=1.2.0
